{
  "schema_version": 1,
  "kind": "julia",
  "width": 320,
  "height": 240,
  "total_frames": 50,
  "fps": 1.0,
  "center_start": [0.0, 0.0],
  "center_end": [-0.03, 0.02],
  "scale_start": 3.0,
  "scale_end": 0.45,
  "julia_c": [-0.835, -0.2321],
  "max_iter": 224,
  "color_seed": 79,
  "stimulus_condition": {
    "condition_id": "julia_zoom_h_50f",
    "condition_family": "fractal",
    "temporal_policy": "ordered",
    "semantic_load": "low",
    "deterministic": true,
    "source_kind": "generated",
    "comparison_role": "source_variant",
    "description": "Independent 50-frame Julia zoom for c=-0.835-0.2321i."
  }
}
